moveread/notifications/__init__.py
moveread/notifications/main.py
moveread_notifications-0.1.2.dist-info/METADATA
moveread_notifications-0.1.2.dist-info/WHEEL
moveread_notifications-0.1.2.dist-info/top_level.txt
moveread_notifications-0.1.2.dist-info/RECORD
