Metadata-Version: 2.1
Name: moveread-notifications
Version: 0.1.2
Summary: APIs for moveread-notifications
Author-email: Marcel Claramunt <marcel@moveread.com>
Project-URL: repo, https://github.com/moveread/notifications.git
Requires-Python: >=3.10
Requires-Dist: fastapi
Requires-Dist: pushed-over
Requires-Dist: chess-pairings
